adb/__init__.py
adb/adb.py
adb/fastboot.py
adb_api-0.1.1.dist-info/licenses/LICENSE
adb_api-0.1.1.dist-info/METADATA
adb_api-0.1.1.dist-info/WHEEL
adb_api-0.1.1.dist-info/top_level.txt
adb_api-0.1.1.dist-info/RECORD
