Metadata-Version: 2.4
Name: adb-api
Version: 0.1.1
Summary: A simple python library for Android Debug Bridge (ADB)
Author-email: chenxi <chenxi201412@outlook.com>
License-Expression: MIT
Project-URL: Homepage, https://github.com/zhangjiahuichenxi/py-adb
Project-URL: Issues, https://github.com/zhangjiahuichenxi/py-adb/issues
Classifier: Programming Language :: Python :: 3
Classifier: Operating System :: OS Independent
Requires-Python: >=3.9
License-File: LICENSE
Dynamic: license-file
